MANIFEST.in
setup.py
test.py
compoundfield/__init__.py
compoundfield/field.py
django_compound_field.egg-info/PKG-INFO
django_compound_field.egg-info/SOURCES.txt
django_compound_field.egg-info/dependency_links.txt
django_compound_field.egg-info/not-zip-safe
django_compound_field.egg-info/requires.txt
django_compound_field.egg-info/top_level.txt