Metadata-Version: 1.0
Name: django-compound-field
Version: 0.1
Summary: A compound field for Django
Home-page: UNKNOWN
Author: Andreas Kostyrka
Author-email: andreas@kostyrka.org
License: BSD
Platform: UNKNOWN
Classifier: Development Status :: 4 - Beta
Classifier: Environment :: Web Environment
Classifier: Framework :: Django
Classifier: Intended Audience :: Developers
Classifier: License :: OSI Approved :: BSD License
Classifier: Operating System :: OS Independent
Classifier: Programming Language :: Python
Classifier: Topic :: Software Development :: Libraries :: Python Modules
